temboard_agent-9.0.1.data/data/lib/systemd/system/temboard-agent@.service
temboard_agent-9.0.1.data/data/share/temboard-agent/auto_configure.sh
temboard_agent-9.0.1.data/data/share/temboard-agent/preun.sh
temboard_agent-9.0.1.data/data/share/temboard-agent/purge.sh
temboard_agent-9.0.1.data/data/share/temboard-agent/restart-all.sh
temboard_agent-9.0.1.data/data/share/temboard-agent/quickstart/temboard-agent_CHANGEME.key
temboard_agent-9.0.1.data/data/share/temboard-agent/quickstart/temboard-agent_CHANGEME.pem
temboard_agent-9.0.1.data/data/share/temboard-agent/quickstart/temboard-agent_ca_certs_CHANGEME.pem
temboardagent/__init__.py
temboardagent/__main__.py
temboardagent/command.py
temboardagent/core.py
temboardagent/discover.py
temboardagent/errors.py
temboardagent/inventory.py
temboardagent/notification.py
temboardagent/postgres.py
temboardagent/status.py
temboardagent/tools.py
temboardagent/version.py
temboardagent/cli/__init__.py
temboardagent/cli/app.py
temboardagent/cli/discover.py
temboardagent/cli/fetch_key.py
temboardagent/cli/register.py
temboardagent/cli/routes.py
temboardagent/cli/runscript.py
temboardagent/cli/runtask.py
temboardagent/cli/serve.py
temboardagent/cli/tasks.py
temboardagent/cli/web.py
temboardagent/plugins/__init__.py
temboardagent/plugins/activity/__init__.py
temboardagent/plugins/activity/functions.py
temboardagent/plugins/activity/process.py
temboardagent/plugins/administration/__init__.py
temboardagent/plugins/administration/types.py
temboardagent/plugins/dashboard/__init__.py
temboardagent/plugins/dashboard/db.py
temboardagent/plugins/dashboard/metrics.py
temboardagent/plugins/maintenance/__init__.py
temboardagent/plugins/maintenance/functions.py
temboardagent/plugins/monitoring/__init__.py
temboardagent/plugins/monitoring/db.py
temboardagent/plugins/monitoring/inventory.py
temboardagent/plugins/monitoring/openmetrics.py
temboardagent/plugins/monitoring/output.py
temboardagent/plugins/monitoring/probes.py
temboard_agent-9.0.1.dist-info/LICENSE
temboard_agent-9.0.1.dist-info/METADATA
temboard_agent-9.0.1.dist-info/WHEEL
temboard_agent-9.0.1.dist-info/entry_points.txt
temboard_agent-9.0.1.dist-info/top_level.txt
temboard_agent-9.0.1.dist-info/RECORD
