Metadata-Version: 2.1
Name: temboard-agent
Version: 9.0.1
Summary: PostgreSQL Remote Control Agent
Home-page: https://labs.dalibo.com/temboard
Author: Dalibo
Author-email: contact@dalibo.com
License: PostgreSQL
Platform: UNKNOWN
Classifier: Environment :: No Input/Output (Daemon)
Classifier: Intended Audience :: System Administrators
Classifier: License :: OSI Approved
Classifier: Operating System :: POSIX :: Linux
Classifier: Programming Language :: Python
Classifier: Programming Language :: Python :: 3
Classifier: Topic :: Database :: Database Engines/Servers
Classifier: Topic :: System :: Monitoring
Requires-Python: ~=3.5
Requires-Dist: bottle (<0.13,>=0.12)
Requires-Dist: cryptography
